abi_dehumanizer/__init__.py
abi_dehumanizer/lib.py
abi_dehumanizer-0.1.dist-info/METADATA
abi_dehumanizer-0.1.dist-info/WHEEL
abi_dehumanizer-0.1.dist-info/top_level.txt
abi_dehumanizer-0.1.dist-info/RECORD
