Metadata-Version: 2.1
Name: abi_dehumanizer
Version: 0.1
Summary: A parser for transforming human-readable ABI strings into a format compatible with eth_abi.decode()
Home-page: https://github.com/0xSt1ng3R/abi-dehumanizer
Author: 0xSt1ng3R
